[
	{
		"back_link": "70517b",
		"code": "70517a",
		"faction_code": "encounter",
		"name": "Searching for the Mask",
		"octgn_id": "07741c02-2afb-5d7c-8088-7da437000017",
		"pack_code": "iron_man_noir_by_merlin",
		"position": 11,
		"quantity": 1,
		"set_code": "iron_man_noir_expedition_by_merlin",
		"set_position": 1,
		"text": "[[expedition.\n]]<b>Setup</b>: Set this card aside.\n<b>Forced Response</b>: After you place a clue counter here, if there are at least 3 clue counters here, flip this card and put Jade Mask into play under any player's control.\n<i>April, 30 1939, 19th day across the jungle.</i>",
		"type_code": "obligation"
	},
	{
		"back_link": "70518b",
		"code": "70518a",
		"faction_code": "encounter",
		"name": "Explore the Alterworld",
		"octgn_id": "07741c02-2afb-5d7c-8088-7da437000018",
		"pack_code": "iron_man_noir_by_merlin",
		"position": 12,
		"quantity": 1,
		"set_code": "iron_man_noir_expedition_by_merlin",
		"set_position": 2,
		"text": "[[expedition.\n]]<b>Setup</b>: Set this card aside.\n<b>Forced Response</b>: After you place a clue counter here, if there are at least 3 clue counters here, flip this card and put Mark II Armor into play under your control.\n<i>Mayan legends tell us that the path to the alterworld was under the ground.</i>",
		"type_code": "obligation"
	},
	{
		"back_link": "70519b",
		"code": "70519a",
		"faction_code": "encounter",
		"name": "Explore Atlantis",
		"octgn_id": "07741c02-2afb-5d7c-8088-7da437000019",
		"pack_code": "iron_man_noir_by_merlin",
		"position": 13,
		"quantity": 1,
		"set_code": "iron_man_noir_expedition_by_merlin",
		"set_position": 3,
		"text": "[[expedition.\n]]<b>Setup</b>: Set this card aside.\n<b>Forced Response</b>: After you place a clue counter here, if there are at least 3 clue counters here, flip this card and put Neptune Trident into play under any player's control.\n<i>According to Platon, Atlantis was built on an island beyond the pillars of Herakles.</i>",
		"type_code": "obligation"
	},
	{
		"back_link": "70520b",
		"code": "70520a",
		"faction_code": "encounter",
		"name": "Save Pepper",
		"octgn_id": "07741c02-2afb-5d7c-8088-7da437000020",
		"pack_code": "iron_man_noir_by_merlin",
		"position": 14,
		"quantity": 1,
		"set_code": "iron_man_noir_expedition_by_merlin",
		"set_position": 4,
		"text": "[[expedition.\n]]<b>Setup</b>: Set this card aside.\nTreat Pepper Potts' text box as if it were blank (except for [[traits]]).\n<b>Forced Response</b>: After you place a clue counter here, if there are at least 3 clue counters here, flip this card and put Moto-Armor into play under your control.",
		"type_code": "obligation"
	},
	{
		"back_link": "70521b",
		"code": "70521a",
		"faction_code": "encounter",
		"name": "Explore the Pyramid",
		"octgn_id": "07741c02-2afb-5d7c-8088-7da437000021",
		"pack_code": "iron_man_noir_by_merlin",
		"position": 15,
		"quantity": 1,
		"set_code": "iron_man_noir_expedition_by_merlin",
		"set_position": 5,
		"text": "[[expedition.\n]]<b>Setup</b>: Set this card aside.\n<b>Forced Response</b>: After you place a clue counter here, if there are at least 3 clue counters here, flip this card and put Orichalque into play under any player's control.",
		"type_code": "obligation"
	},
	{
		"code": "70522",
		"faction_code": "encounter",
		"name": "Nazis' Pressure",
		"octgn_id": "07741c02-2afb-5d7c-8088-7da437000022",
		"pack_code": "iron_man_noir_by_merlin",
		"position": 16,
		"quantity": 1,
		"set_code": "iron_man_noir_by_merlin",
		"text": "[[expedition.\n]]You may flip to hero form.\n<b>Response</b>: After you place a clue counter here, if there are at least 3 clue counters here, remove Nazis' Pressure from the game.\n[hazard]",
		"type_code": "obligation"
	},
	{
		"attack": 2,
		"attack_star": true,
		"boost": 2,
		"code": "70523",
		"faction_code": "encounter",
		"health": 5,
		"is_unique": true,
		"name": "Doctor Zemo",
		"octgn_id": "07741c02-2afb-5d7c-8088-7da437000023",
		"pack_code": "iron_man_noir_by_merlin",
		"position": 17,
		"quantity": 1,
		"scheme": 2,
		"set_code": "iron_man_noir_by_merlin_nemesis",
		"set_position": 1,
		"text": "[star]<b> Forced interrupt</b>: When Doctor Zemo attacks you, that attack deals indirect damage.\n<i>(Iron Man Noir's nemesis minion.)</i>",
		"traits": "Elite. Hydra.",
		"type_code": "minion"
	},
	{
		"base_threat": 2,
		"base_threat_fixed": true,
		"boost": 3,
		"code": "70524",
		"faction_code": "encounter",
		"name": "Artifact Theft",
		"octgn_id": "07741c02-2afb-5d7c-8088-7da437000024",
		"pack_code": "iron_man_noir_by_merlin",
		"position": 18,
		"quantity": 1,
		"set_code": "iron_man_noir_by_merlin_nemesis",
		"set_position": 2,
		"text": "<i>“Sorry Tony!”\n</i>Hinder 1[per_hero] <b>When Revealed</b>: choose an [[artefact ]]upgrade in play and place it facedown under Artifact Theft.\n<b>When Defeated</b>: Put the [[artefact ]]upgrade Artifact Theft into play.\n[amplify]",
		"type_code": "side_scheme"
	},
	{
		"boost": 2,
		"code": "70525",
		"faction_code": "encounter",
		"name": "Backfire",
		"octgn_id": "07741c02-2afb-5d7c-8088-7da437000025",
		"pack_code": "iron_man_noir_by_merlin",
		"position": 19,
		"quantity": 2,
		"set_code": "iron_man_noir_by_merlin_nemesis",
		"set_position": 3,
		"text": "<b>When Revealed</b>: Choose to either deal 1 damage to your hero for each [[artefact ]]upgrade under your control (to a maximum of 3), or discard an upgrade you control.\n<i>“No, it's not possible!” </i>—<i>Tony</i>",
		"type_code": "treachery"
	},
	{
		"boost": 3,
		"code": "70527",
		"faction_code": "encounter",
		"name": "Conversion",
		"octgn_id": "07741c02-2afb-5d7c-8088-7da437000027",
		"pack_code": "iron_man_noir_by_merlin",
		"position": 20,
		"quantity": 1,
		"set_code": "iron_man_noir_by_merlin_nemesis",
		"set_position": 5,
		"text": "<b>When Revealed</b>: Flip to alter-ego form. Discard 1 card from your hand for each [[artefact ]]upgrade you control (to a maximum de 3).\n<i>Z.E.M.O. is not person, it is a drug.</i>",
		"type_code": "treachery"
	}
]
