[
    {
        "attack": 1,
        "back_link": "207301b",
        "code": "207301a",
        "deck_limit": 1,
        "defense": 1,
        "duplicate_of_name": "",
        "faction_code": "hero",
        "flavor": "\"I'm sick of you amateurs getting in my way!\"",
        "hand_size": 5,
        "health": 9,
        "is_unique": true,
        "name": "Night Thrasher",
        "octgn_id": "e3708e9e-e077-44b9-9a46-7c41b3073001",
        "pack_code": "night_thrasher_by_designhacker",
        "position": 1,
        "quantity": 1,
        "set_code": "night_thrasher_by_designhacker",
        "text": "<i>Varial Heelflip</i> — <b>Response</b>: After you play a [[Skill]] card, flip the Battle Board upgrade. (Limit once per phase.)",
        "thwart": 1,
        "traits": "Avenger. New Warrior.",
        "type_code": "hero"
    },
    {
        "code": "207301b",
        "deck_limit": 1,
        "duplicate_of_name": "",
        "faction_code": "hero",
        "hand_size": 6,
        "health": 9,
        "hidden": true,
        "is_unique": true,
        "name": "Dwayne Taylor",
        "octgn_id": "e3708e9e-e077-44b9-9a46-7c41b3073001",
        "pack_code": "night_thrasher_by_designhacker",
        "position": 1,
        "quantity": 1,
        "recover": 3,
        "set_code": "night_thrasher_by_designhacker",
        "text": "<i>Tech Deck</i> — During deck-building you may include up to 4 [[Skill]] cards in your deck from aspects other than your own.\n<i>Manual</i> — <b>Action</b>: Shuffle X [[Skill]] cards from your hand into your deck → draw X cards. (Limit once per round.)",
        "traits": "Genius.",
        "type_code": "alter_ego"
    },
    {
        "code": "207302",
        "cost": 2,
        "deck_limit": 2,
        "duplicate_of_name": "",
        "faction_code": "hero",
        "is_unique": false,
        "name": "Disaster",
        "octgn_id": "e3708e9e-e077-44b9-9a46-7c41b3073002",
        "pack_code": "night_thrasher_by_designhacker",
        "position": 2,
        "quantity": 2,
        "resource_physical": 1,
        "set_code": "night_thrasher_by_designhacker",
        "set_position": 1,
        "text": "<b>Hero Action</b>: (<i>attack/thwart</i>): Flip the Battle Board upgrade. Then, if it has the:\n• [[Vehicle]] trait, remove 3 threat from a scheme.\n• [[Weapon]] trait, deal 4 damage to an enemy.<i></i>",
        "traits": "Attack. Skill. Thwart.",
        "type_code": "event"
    },
    {
        "code": "207303",
        "cost": 1,
        "deck_limit": 2,
        "duplicate_of_name": "",
        "faction_code": "hero",
        "flavor": "\"Such a strategy has succeeded many times on the field of battle.\"—Ares",
        "is_unique": false,
        "name": "Drop In",
        "octgn_id": "e3708e9e-e077-44b9-9a46-7c41b3073003",
        "pack_code": "night_thrasher_by_designhacker",
        "position": 3,
        "quantity": 2,
        "resource_wild": 1,
        "set_code": "night_thrasher_by_designhacker",
        "set_position": 3,
        "text": "<b>Hero Response</b>: After you change to hero form, if the Battle Board upgrade has the:\n• [[Vehicle]] trait, confuse an enemy.\n• [[Weapon]] trait, stun an enemy.",
        "traits": "Skill.",
        "type_code": "event"
    },
    {
        "code": "207304",
        "cost": 1,
        "deck_limit": 2,
        "duplicate_of_name": "",
        "faction_code": "hero",
        "is_unique": false,
        "name": "Kickflip",
        "octgn_id": "e3708e9e-e077-44b9-9a46-7c41b3073004",
        "pack_code": "night_thrasher_by_designhacker",
        "position": 4,
        "quantity": 4,
        "resource_physical": 1,
        "set_code": "night_thrasher_by_designhacker",
        "set_position": 5,
        "text": "If the last card you played this round was a Night Thrasher event, reduce the cost to play this card by 1.\n<b>Hero Action</b> (attack): Flip the Battle Board upgrade and deal 1 damage to an enemy. Draw 1 card.",
        "traits": "Attack. Skill.",
        "type_code": "event"
    },
    {
        "code": "207305",
        "cost": 3,
        "deck_limit": 1,
        "duplicate_of_name": "",
        "faction_code": "hero",
        "is_unique": false,
        "name": "Melon Grab",
        "octgn_id": "e3708e9e-e077-44b9-9a46-7c41b3073005",
        "pack_code": "night_thrasher_by_designhacker",
        "position": 5,
        "quantity": 1,
        "resource_physical": 1,
        "set_code": "night_thrasher_by_designhacker",
        "set_position": 9,
        "text": "<b>Action</b>: (<i>attack</i>): Deal 8 damage to an enemy. If the Battle Board upgrade has the:\n• [[Vehicle]] trait, damage from this attack can be divided among enemies as you choose.\n• [[Weapon]] trait, this attack gains piercing and overkill.",
        "traits": "Attack. Skill.",
        "type_code": "event"
    },
    {
        "code": "207306",
        "cost": 1,
        "deck_limit": 2,
        "duplicate_of_name": "",
        "faction_code": "hero",
        "is_unique": false,
        "name": "Tailblock",
        "octgn_id": "e3708e9e-e077-44b9-9a46-7c41b3073006",
        "pack_code": "night_thrasher_by_designhacker",
        "position": 6,
        "quantity": 2,
        "resource_mental": 1,
        "set_code": "night_thrasher_by_designhacker",
        "set_position": 10,
        "text": "Hero <b>Interrupt</b> (<i>defense</i>): When you would take any amount of damage, if the Battle Board upgrade has the:\n• [[Vehicle]] trait, prevent 1 of that damage and draw 2 cards.\n• [[Weapon]] trait, prevent 3 of that damage.",
        "traits": "Defense. Skill.",
        "type_code": "event"
    },
    {
        "code": "207307",
        "cost": 2,
        "deck_limit": 1,
        "duplicate_of_name": "",
        "faction_code": "hero",
        "flavor": "Location.",
        "is_unique": false,
        "name": "The Mancave",
        "octgn_id": "e3708e9e-e077-44b9-9a46-7c41b3073007",
        "pack_code": "night_thrasher_by_designhacker",
        "position": 7,
        "quantity": 1,
        "resource_wild": 1,
        "set_code": "night_thrasher_by_designhacker",
        "set_position": 12,
        "text": "<b>Alter-Ego Response</b>: After you change form, heal 1 damage from your identity.\n<b>Hero Response</b>: After you change form, reduce the resource cost of the next [[Skill]] card you play this turn by 1.",
        "traits": "Location.",
        "type_code": "support"
    },
    {
        "back_link": "207308b",
        "code": "207308a",
        "cost": 0,
        "deck_limit": 1,
        "duplicate_of_name": "",
        "faction_code": "hero",
        "is_unique": true,
        "name": "Battle Board",
        "octgn_id": "e3708e9e-e077-44b9-9a46-7c41b3073008",
        "pack_code": "night_thrasher_by_designhacker",
        "permanent": true,
        "position": 8,
        "quantity": 1,
        "set_code": "night_thrasher_by_designhacker",
        "set_position": 13,
        "text": "Permanent. Setup.\nNight Thrasher gets +1 THW and gains agile 1 (reduce damage from attacks with boost cards by 1).\n<b>Response</b>: After you flip to this side, remove 1 threat from a scheme.",
        "traits": "Vehicle.",
        "type_code": "upgrade"
    },
    {
        "code": "207308b",
        "cost": 0,
        "deck_limit": 1,
        "duplicate_of_name": "",
        "faction_code": "hero",
        "hidden": true,
        "is_unique": true,
        "name": "Battle Board",
        "octgn_id": "e3708e9e-e077-44b9-9a46-7c41b3073008",
        "pack_code": "night_thrasher_by_designhacker",
        "permanent": true,
        "position": 8,
        "quantity": 1,
        "set_code": "night_thrasher_by_designhacker",
        "set_position": 13,
        "text": "Permanent.\nNight Thrasher gets +1 ATK and +1 DEF.\n<b>Hero Response</b>: After you flip to this side, deal 1 damage to an enemy.",
        "traits": "Weapon.",
        "type_code": "upgrade"
    },
    {
        "code": "207309",
        "cost": 3,
        "deck_limit": 1,
        "duplicate_of_name": "",
        "faction_code": "hero",
        "is_unique": true,
        "name": "Escrima Sticks",
        "octgn_id": "e3708e9e-e077-44b9-9a46-7c41b3073009",
        "pack_code": "night_thrasher_by_designhacker",
        "position": 9,
        "quantity": 1,
        "resource_energy": 1,
        "set_code": "night_thrasher_by_designhacker",
        "set_position": 14,
        "text": "While the Battle Board upgrade has the [[Vehicle]] trait, your attacks gain piercing and overkill.\n<b>Hero Action</b> (<i>attack</i>): Deal 6 damage to an enemy. Shuffle this card into your deck.",
        "traits": "Weapon.",
        "type_code": "upgrade"
    },
    {
        "code": "207310",
        "cost": 1,
        "deck_limit": 1,
        "duplicate_of_name": "",
        "faction_code": "hero",
        "flavor": "\"I think of myself as a teacher of hard lessons.\" -Night Thrasher",
        "is_unique": false,
        "name": "Multi-skilled",
        "octgn_id": "e3708e9e-e077-44b9-9a46-7c41b3073010",
        "pack_code": "night_thrasher_by_designhacker",
        "position": 10,
        "quantity": 1,
        "set_code": "night_thrasher_by_designhacker",
        "set_position": 15,
        "text": "<b>Resource</b>: Exhaust Multi-Skilled → generate a [wild] resource for a [[Skill]] card.",
        "traits": "Condition.",
        "type_code": "upgrade"
    },
    {
        "code": "207311",
        "cost": 3,
        "deck_limit": 1,
        "duplicate_of_name": "",
        "faction_code": "hero",
        "is_unique": false,
        "name": "Prewind Stance",
        "octgn_id": "e3708e9e-e077-44b9-9a46-7c41b3073011",
        "pack_code": "night_thrasher_by_designhacker",
        "position": 11,
        "quantity": 1,
        "resource_energy": 1,
        "set_code": "night_thrasher_by_designhacker",
        "set_position": 16,
        "text": "Night Thrasher gets +1 DEF and gains retaliate 1.\n<b>Hero Interrupt</b>: When your turn or the villain phase begins, exhaust Prewind Stance → flip the Battle Board upgrade.",
        "traits": "Skill.",
        "type_code": "upgrade"
    }
]
