[
    {
        "boost": 1,
        "code": "204311",
        "faction_code": "encounter",
        "name": "Silver Down",
        "octgn_id": "a23e01f9-a42f-416f-a779-f919be043011",
        "pack_code": "Silver_Surfer_by_Hax",
        "position": 11,
        "quantity": 1,
        "set_code": "Silver_Surfer_by_Hax",
        "text": "<b><i>Give to the Norrin Radd player.</i></b>\nYou may flip to alter-ego form. Choose:\n. Exhaust Norrin Radd \u2192 remove Silver Down from the game.\n. Summon Dawn Greenwood and remove her from the game \u2192 remove Silver Down from the game.",
        "type_code": "obligation"
    },
    {
        "attack": 2,
        "code": "204312",
        "faction_code": "encounter",
         "health": 3,
        "is_unique": true,
        "name": "Galactus",
        "octgn_id": "a23e01f9-a42f-416f-a779-f919be043012",
        "pack_code": "Silver_Surfer_by_Hax",
        "position": 12,
        "quantity": 1,
        "scheme": 2,
        "set_code": "Silver_Surfer_by_Hax_nemesis",
        "set_position": 1,
        "text": "Villainous.\n<b>When Revealed</b>: Reveal The World Eater and put it into play engaged with you.\n<b>When Defeated</b>: Remove Galactus from the game.\n<i>(Silver Surfer's nemesis minion.)</i>",
        "traits": "Cosmic. Elite.",
        "type_code": "minion"
    },
    {
        "attack": 0,
        "code": "204313",
        "faction_code": "encounter",
        "flavor": "\u201cYou will claim no victory here today, Norrin Radd. True, you may delay me for a time, but you cannot possibly stop me.\u201d",
        "health": 5,
        "is_unique": true,
        "name": "The World Eater",
        "octgn_id": "a23e01f9-a42f-416f-a779-f919be043013",
        "pack_code": "Silver_Surfer_by_Hax",
        "position": 13,
        "quantity": 1,
        "scheme": 0,
        "set_code": "Silver_Surfer_by_Hax_nemesis",
        "set_position": 2,
        "text": "Galactus cannot take damage and his attacks gain overkill.\n<b>When Defeated</b>: Remove The World Eater from the game.",
        "traits": "Cosmic. Elite.",
        "type_code": "minion"
    },
    {
        "base_threat": 2,
        "code": "204314",
        "faction_code": "encounter",
        "flavor": "Galactus is using The Power Cosmic to steal the heroes' life force!",
        "name": "The Life Stealer",
        "octgn_id": "a23e01f9-a42f-416f-a779-f919be043014",
        "pack_code": "Silver_Surfer_by_Hax",
        "position": 14,
        "quantity": 1,
        "set_code": "Silver_Surfer_by_Hax_nemesis",
        "set_position": 3,
        "text": "All friendly characters get -1 ATK.\n<b>When Revealed</b>: Place 1 additional threat here for each friendly character in play.",
        "type_code": "side_scheme",
        "boost": 2
    },
    {
        "attack_star": true,
        "boost": 1,
        "code": "204315",
        "faction_code": "encounter",
        "flavor": "\u201cThe only power you possess, is the power I bestowed upon you.\u201d",
        "name": "Cosmic Power",
        "octgn_id": "a23e01f9-a42f-416f-a779-f919be043015",
        "pack_code": "Silver_Surfer_by_Hax",
        "position": 15,
        "quantity": 2,
        "set_code": "Silver_Surfer_by_Hax_nemesis",
        "set_position": 4,
        "text": "Attach to Galactus. If you cannot, attach to the villain.\n[star] Attached enemy's attacks gain overkill.\n<b>Hero Action</b>: Take 3 damage \u2192 remove Cosmic Power from the game.",
        "type_code": "attachment"
    }
]